wtforms_aceditor/__init__.py
wtforms_aceditor-0.0.2.dist-info/LICENSE
wtforms_aceditor-0.0.2.dist-info/METADATA
wtforms_aceditor-0.0.2.dist-info/WHEEL
wtforms_aceditor-0.0.2.dist-info/top_level.txt
wtforms_aceditor-0.0.2.dist-info/RECORD
