Metadata-Version: 2.1
Name: wtforms-aceditor
Version: 0.0.2
Summary: wtforms aceditor component
Home-page: https://github.com/WorldException/wtforms_aceditor
Author: Stoyanov Evgeny
Author-email: quick.es@gmail.com
License: MIT License
Project-URL: Homepage, https://github.com/WorldException/wtforms_aceditor
Keywords: wtforms,flask,aceditor
Classifier: License :: OSI Approved :: MIT License
Classifier: Programming Language :: Python
Classifier: Programming Language :: Python :: 3
Requires: wtforms
Requires: markupsafe
Requires-Python: >=3.9
License-File: LICENSE
Requires-Dist: wtforms <=2.3.3
Requires-Dist: markupsafe
Provides-Extra: dev
Requires-Dist: flask ; extra == 'dev'
Requires-Dist: flask-wtf ; extra == 'dev'
